README.md
setup.py
alfa_cli/__init__.py
alfa_cli/__main__.py
alfa_cli/cli.py
alfa_cli/config.py
alfa_cli.egg-info/PKG-INFO
alfa_cli.egg-info/SOURCES.txt
alfa_cli.egg-info/dependency_links.txt
alfa_cli.egg-info/entry_points.txt
alfa_cli.egg-info/requires.txt
alfa_cli.egg-info/top_level.txt
alfa_cli/commands/__init__.py
alfa_cli/commands/alfa.py
alfa_cli/commands/configure.py
alfa_cli/commands/resource.py
alfa_cli/commands/secrets.py
alfa_cli/commands/algorithm/__init__.py
alfa_cli/commands/algorithm/deploy.py
alfa_cli/commands/algorithm/initialize.py
alfa_cli/commands/algorithm/invoke.py
alfa_cli/commands/algorithm/train.py
alfa_cli/commands/integration/__init__.py
alfa_cli/commands/integration/deploy.py
alfa_cli/commands/integration/initialize.py
alfa_cli/commands/integration/invoke.py
alfa_cli/common/__init__.py
alfa_cli/common/click.py
alfa_cli/common/exceptions.py
alfa_cli/common/factories.py
alfa_cli/common/logger.py
alfa_cli/common/utils.py
alfa_cli/common/helpers/__init__.py
alfa_cli/common/helpers/file.py
alfa_cli/common/helpers/ignore.py
alfa_cli/common/helpers/snapshot.py
alfa_cli/lib/__init__.py
alfa_cli/lib/tester.py
alfa_cli/lib/initializer/__init__.py
alfa_cli/lib/initializer/files.py
alfa_cli/lib/initializer/specification.py
alfa_cli/lib/runner/__init__.py
alfa_cli/lib/runner/node.py
alfa_cli/lib/runner/python.py
alfa_cli/lib/runner/utils.py
alfa_cli/lib/trainer/__init__.py
alfa_cli/lib/trainer/build_configuration.py
alfa_cli/lib/trainer/response.py
alfa_cli/lib/trainer/builders/__init__.py
alfa_cli/lib/trainer/builders/methods.py
alfa_cli/lib/trainer/builders/search_options.py
bin/alfa-complete.sh
bin/alfa-complete.zsh